Workbook

Sheet Dashboard
A1: Cyber Risk Dashboard — PayWave Solutions Pte. Ltd.
A3: Total Risks Identified | C3: Critical (Residual) | E3: High (Residual) | G3: Medium (Residual) | I3: Low (Residual)
A4: =COUNTA('Risk Register'!A5:A20) -> 16 | C4: =COUNTIF('Risk Register'!T5:T20,"Critical") -> 2 | E4: =COUNTIF('Risk Register'!T5:T20,"High") -> 5 | G4: =COUNTIF('Risk Register'!T5:T20,"Medium") -> 7 | I4: =COUNTIF('Risk Register'!T5:T20,"Low") -> 2
A7: Residual Risk Distribution | D7: Risks by NIST CSF Function | G7: Treatment Decisions
A8: Rating | B8: Count | D8: Function | E8: Count | G8: Decision | H8: Count
A9: Critical | B9: =COUNTIF('Risk Register'!T5:T20,"Critical") -> 2 | D9: Identify (ID) | E9: =COUNTIF('Risk Register'!B5:B20,"Identify (ID)") -> 2 | G9: Mitigate | H9: =COUNTIF('Risk Register'!V5:V20,"Mitigate") -> 15
A10: High | B10: =COUNTIF('Risk Register'!T5:T20,"High") -> 5 | D10: Protect (PR) | E10: =COUNTIF('Risk Register'!B5:B20,"Protect (PR)") -> 11 | G10: Accept | H10: =COUNTIF('Risk Register'!V5:V20,"Accept") -> 1
A11: Medium | B11: =COUNTIF('Risk Register'!T5:T20,"Medium") -> 7 | D11: Detect (DE) | E11: =COUNTIF('Risk Register'!B5:B20,"Detect (DE)") -> 1 | G11: Transfer | H11: =COUNTIF('Risk Register'!V5:V20,"Transfer") -> 0
A12: Low | B12: =COUNTIF('Risk Register'!T5:T20,"Low") -> 2 | D12: Respond (RS) | E12: =COUNTIF('Risk Register'!B5:B20,"Respond (RS)") -> 1 | G12: Avoid | H12: =COUNTIF('Risk Register'!V5:V20,"Avoid") -> 0
D13: Recover (RC) | E13: =COUNTIF('Risk Register'!B5:B20,"Recover (RC)") -> 1
A15: Treatment Budget Summary
A16: Priority | B16: Count | C16: Est. Budget (SGD)
A17: P1 (Months 1–3) | B17: =COUNTIF('Treatment Plan'!G5:G19,"P1") -> 6 | C17: $115,000 – $185,000
A18: P2 (Months 4–6) | B18: =COUNTIF('Treatment Plan'!G5:G19,"P2") -> 7 | C18: $76,000 – $127,000
A19: P3 (Months 7–12) | B19: =COUNTIF('Treatment Plan'!G5:G19,"P3") -> 2 | C19: $8,000 – $15,000
A20: TOTAL (Year 1) | C20: $199,000 – $327,000

Sheet Risk Methodology
A1: Cyber Risk Assessment Methodology — PayWave Solutions Pte. Ltd.
A2: Aligned to ISO 27005, NIST SP 800-30, and MAS TRM Guidelines
A4: 1. Purpose
A5: This document defines the risk assessment methodology used to identify, analyse, evaluate, and treat information security risks for PayWave Solutions Pte. Ltd. The methodology applies to all information assets within the ISMS scope and supports compliance with ISO 27001:2022 Clause 6.1.2, MAS TRM Guidelines, PDPA, and PCI DSS.
A9: 2. Likelihood Scale
A10: Score | B10: Rating | C10: Description | D10: Frequency Benchmark
A11: 1 | B11: Very Low | C11: The threat source is unlikely to exploit the vulnerability. Strong preventive controls exist. | D11: Less than once in 5 years
A12: 2 | B12: Low | C12: The threat source could exploit the vulnerability but conditions are unfavourable or controls are in place. | D12: Once every 2–5 years
A13: 3 | B13: Moderate | C13: The threat source is motivated and capable. Controls exist but are not comprehensive. | D13: Once per year
A14: 4 | B14: High | C14: The threat source is highly motivated and capable. Controls are weak or partial. | D14: Multiple times per year
A15: 5 | B15: Very High | C15: The threat source is almost certain to exploit the vulnerability. Controls are absent or ineffective. | D15: Monthly or more frequently
A17: 3. Impact Scale
A18: Score | B18: Rating | C18: Financial Impact | D18: Operational Impact | E18: Regulatory Impact | F18: Reputational Impact
A19: 1 | B19: Negligible | C19: < SGD 10,000 | D19: Minor inconvenience, no service disruption | E19: No regulatory interest | F19: No media attention
A20: 2 | B20: Minor | C20: SGD 10,000 – 50,000 | D20: Brief service degradation (<1 hour), workaround available | E20: Informal regulatory inquiry | F20: Limited social media mentions
A21: 3 | B21: Moderate | C21: SGD 50,000 – 250,000 | D21: Service disruption 1–4 hours, partial loss of capability | E21: Formal MAS inquiry or PDPC investigation | F21: Local media coverage
A22: 4 | B22: Major | C22: SGD 250,000 – 1,000,000 | D22: Service outage 4–24 hours, significant data loss | E22: MAS enforcement action, PDPA fine up to SGD 1M | F22: National media coverage, customer churn
A23: 5 | B23: Catastrophic | C23: > SGD 1,000,000 | D23: Extended outage >24 hours, total loss of critical data | E23: MAS licence revocation threat, criminal prosecution | F23: Sustained negative coverage, mass customer exodus
A25: 4. Risk Rating Thresholds
A26: Risk Score Range | B26: Risk Rating | C26: Response Required | D26: Escalation Level
A27: 20–25 | B27: Critical | C27: Immediate action required within 48 hours. Risk owner and CISO must approve treatment plan. | D27: Board / CEO
A28: 12–19 | B28: High | C28: Action required within 30 days. Dedicated project with named owner and tracked milestones. | D28: CISO / CTO
A29: 6–11 | B29: Medium | C29: Action required within 90 days. Scheduled into next planning cycle. | D29: Department Head
A30: 1–5 | B30: Low | C30: Monitor and review at next scheduled risk review. Accept if within risk appetite. | D30: Risk Owner
A32: 5. Risk Appetite Statement
A33: PayWave Solutions has a LOW risk appetite for information security risks due to its position as a regulated financial institution under MAS oversight. No Critical risks may be accepted. High risks may only be accepted with written CISO and CEO approval, time-bound to a maximum of 90 days. Medium and Low risks may be accepted by the risk owner with documented justification.

Sheet Risk Register
A1: Cyber Risk Register — PayWave Solutions Pte. Ltd.
A2: Assessment Date: 15 March 2026 | NIST CSF Aligned | Version 1.0 | Classification: CONFIDENTIAL
A4: Risk ID | B4: NIST CSF Function | C4: Risk Category | D4: Risk Title | E4: Risk Description | F4: Threat Source | G4: Threat Action | H4: Vulnerability | I4: Asset at Risk | J4: Data Classification | K4: Likelihood (1-5) | L4: Impact (1-5) | M4: Inherent Risk Score | N4: Inherent Rating | O4: Existing Controls | P4: Control Effectiveness | Q4: Residual Likelihood | R4: Residual Impact | S4: Residual Risk Score | T4: Residual Rating | U4: Risk Owner | V4: Treatment Decision | W4: Treatment Reference
A5: CRR-001 | B5: Protect (PR) | C5: Access Control | D5: Privileged access abuse by developers | E5: Software developers retain standing production database access, enabling unauthorised viewing, modification, or exfiltration of customer PII and payment transaction data. | F5: Insider (developer) | G5: Privilege abuse / data exfiltration | H5: No PAM solution; developers have standing prod access; no session recording | I5: Production database (PostgreSQL) | J5: Restricted (PII + payment data) | K5: 4 | L5: 5 | M5: =K5*L5 -> 20 | N5: =IF(M5>=20,"Critical",IF(M5>=12,"High",IF(M5>=6,"Medium","Low"))) -> Critical | O5: PCI DSS SoD for card data path only; code review required for PRs; annual background checks | P5: Weak | Q5: 3 | R5: 4 | S5: =Q5*R5 -> 12 | T5: =IF(S5>=20,"Critical",IF(S5>=12,"High",IF(S5>=6,"Medium","Low"))) -> High | U5: CTO | V5: Mitigate | W5: TRP-001
A6: CRR-002 | B6: Detect (DE) | C6: Security Monitoring | D6: Ransomware attack with delayed detection | E6: Ransomware deployed on corporate network goes undetected for hours or days due to absence of EDR and SIEM, encrypting critical business systems and potentially exfiltrating data before encryption. | F6: External (cybercriminal group) | G6: Malware deployment / double extortion | H6: No EDR on endpoints; no SIEM; CloudWatch monitors infra only; no behavioural analysis | I6: Corporate IT systems + file servers | J6: Confidential (business data) | K6: 4 | L6: 5 | M6: =K6*L6 -> 20 | N6: =IF(M6>=20,"Critical",IF(M6>=12,"High",IF(M6>=6,"Medium","Low"))) -> Critical | O6: Antivirus (signature-based); CloudWatch CPU/memory alerts; quarterly penetration testing | P6: Weak | Q6: 4 | R6: 5 | S6: =Q6*R6 -> 20 | T6: =IF(S6>=20,"Critical",IF(S6>=12,"High",IF(S6>=6,"Medium","Low"))) -> Critical | U6: CISO | V6: Mitigate | W6: TRP-002
A7: CRR-003 | B7: Protect (PR) | C7: Cloud Security | D7: S3 bucket misconfiguration exposing customer data | E7: AWS S3 bucket configured as publicly accessible due to developer error or IaC misconfiguration, exposing customer PII, merchant data, or transaction records to the internet. | F7: Human error (developer) | G7: Misconfiguration / data exposure | H7: No CSPM tool; IaC not enforced; no automated public-access detection; ad-hoc AWS resource creation | I7: AWS S3 buckets (customer data) | J7: Restricted (PII) | K7: 4 | L7: 5 | M7: =K7*L7 -> 20 | N7: =IF(M7>=20,"Critical",IF(M7>=12,"High",IF(M7>=6,"Medium","Low"))) -> Critical | O7: Basic AWS tagging policy; manual reviews during quarterly security check; AWS GuardDuty (limited) | P7: Weak | Q7: 4 | R7: 5 | S7: =Q7*R7 -> 20 | T7: =IF(S7>=20,"Critical",IF(S7>=12,"High",IF(S7>=6,"Medium","Low"))) -> Critical | U7: DevOps Lead | V7: Mitigate | W7: TRP-003
A8: CRR-004 | B8: Respond (RS) | C8: Incident Response | D8: PDPA breach notification failure | E8: Data breach affecting customer PII occurs but organisation fails to notify PDPC within the mandatory 72-hour window due to absence of a defined breach notification process, resulting in regulatory enforcement action. | F8: Regulatory non-compliance | G8: Failure to detect and report breach within timeframe | H8: No breach notification SOP; no authority contact register; IR plan covers fraud only; no PDPC escalation path | I8: Organisational (regulatory standing) | J8: N/A (process risk) | K8: 3 | L8: 5 | M8: =K8*L8 -> 15 | N8: =IF(M8>=20,"Critical",IF(M8>=12,"High",IF(M8>=6,"Medium","Low"))) -> High | O8: Fraud-specific IR playbook exists; legal team aware of PDPA obligations (informally) | P8: Weak | Q8: 3 | R8: 5 | S8: =Q8*R8 -> 15 | T8: =IF(S8>=20,"Critical",IF(S8>=12,"High",IF(S8>=6,"Medium","Low"))) -> High | U8: DPO | V8: Mitigate | W8: TRP-004
A9: CRR-005 | B9: Protect (PR) | C9: Vulnerability Management | D9: Exploitation of unpatched critical vulnerability | E9: Publicly disclosed critical vulnerability in production-facing application or infrastructure component remains unpatched beyond vendor advisory window, exploited by threat actor to gain initial access. | F9: External (opportunistic attacker) | G9: Exploitation of known CVE | H9: No continuous vulnerability scanner; quarterly pentests only; no patch SLA defined; no vulnerability register | I9: Production web application + APIs | J9: Restricted (payment data) | K9: 4 | L9: 5 | M9: =K9*L9 -> 20 | N9: =IF(M9>=20,"Critical",IF(M9>=12,"High",IF(M9>=6,"Medium","Low"))) -> Critical | O9: Snyk for code dependencies; quarterly third-party penetration testing; ad-hoc OS patching | P9: Moderate | Q9: 3 | R9: 4 | S9: =Q9*R9 -> 12 | T9: =IF(S9>=20,"Critical",IF(S9>=12,"High",IF(S9>=6,"Medium","Low"))) -> High | U9: DevOps Lead | V9: Mitigate | W9: TRP-005
A10: CRR-006 | B10: Protect (PR) | C10: Identity & Authentication | D10: Credential compromise via phishing | E10: Employee credentials compromised through sophisticated phishing attack targeting engineering or finance staff, providing attacker with initial access to corporate email, cloud accounts, or payment systems. | F10: External (social engineering) | G10: Spear phishing / credential harvesting | H10: Generic annual security training; no role-based phishing awareness; MFA not enforced on all SaaS apps; no email DMARC enforcement | I10: Employee email accounts + SaaS apps | J10: Confidential (business data) | K10: 4 | L10: 4 | M10: =K10*L10 -> 16 | N10: =IF(M10>=20,"Critical",IF(M10>=12,"High",IF(M10>=6,"Medium","Low"))) -> High | O10: Annual phishing simulation (40% fail rate); MFA on AWS console and VPN; Okta SSO for major apps | P10: Moderate | Q10: 3 | R10: 3 | S10: =Q10*R10 -> 9 | T10: =IF(S10>=20,"Critical",IF(S10>=12,"High",IF(S10>=6,"Medium","Low"))) -> Medium | U10: CISO | V10: Mitigate | W10: TRP-006
A11: CRR-007 | B11: Protect (PR) | C11: Data Protection | D11: Data exfiltration via USB or personal cloud | E11: Employee or contractor copies sensitive data (customer PII, source code, financial reports) to personal USB device or cloud storage service, either maliciously or through negligent data handling. | F11: Insider (employee/contractor) | G11: Data theft / negligent data handling | H11: USB ports not restricted; no DLP agent on endpoints; no acceptable use policy; personal cloud storage (Dropbox, Google Drive) accessible | I11: Customer PII + source code + financial data | J11: Restricted / Confidential | K11: 3 | L11: 4 | M11: =K11*L11 -> 12 | N11: =IF(M11>=20,"Critical",IF(M11>=12,"High",IF(M11>=6,"Medium","Low"))) -> High | O11: Full disk encryption on company laptops; exit interviews; annual background checks; NDAs in employment contracts | P11: Moderate | Q11: 3 | R11: 3 | S11: =Q11*R11 -> 9 | T11: =IF(S11>=20,"Critical",IF(S11>=12,"High",IF(S11>=6,"Medium","Low"))) -> Medium | U11: IT Manager | V11: Mitigate | W11: TRP-007
A12: CRR-008 | B12: Protect (PR) | C12: Secure Development | D12: Insecure code deployed to production | E12: Security vulnerabilities (SQL injection, XSS, SSRF, insecure deserialization) introduced in application code due to absence of SAST/DAST in CI/CD pipeline, reaching production and exploitable by external attackers. | F12: Human error (developer) | G12: Introduction of exploitable code defects | H12: No SAST tool in CI/CD; no DAST scanning; no secure coding guidelines; no security champion program; code reviews focus on functionality not security | I12: Payment processing application + APIs | J12: Restricted (payment data) | K12: 4 | L12: 4 | M12: =K12*L12 -> 16 | N12: =IF(M12>=20,"Critical",IF(M12>=12,"High",IF(M12>=6,"Medium","Low"))) -> High | O12: Mandatory code reviews for all PRs; Snyk dependency scanning; quarterly external penetration testing | P12: Moderate | Q12: 3 | R12: 3 | S12: =Q12*R12 -> 9 | T12: =IF(S12>=20,"Critical",IF(S12>=12,"High",IF(S12>=6,"Medium","Low"))) -> Medium | U12: Engineering Lead | V12: Mitigate | W12: TRP-008
A13: CRR-009 | B13: Identify (ID) | C13: Third-Party Risk | D13: Supply chain compromise via SaaS vendor | E13: Critical SaaS vendor (CI/CD platform, cloud monitoring, or communication tool) suffers a security breach, exposing PayWave's data, credentials, or source code through the compromised vendor integration. | F13: Third-party (vendor breach) | G13: Supply chain attack / vendor compromise | H13: No formal TPRM program; no vendor security assessments; no contractual security requirements for SaaS vendors; API keys stored in vendor platforms | I13: Source code + deployment pipelines + internal communications | J13: Confidential | K13: 3 | L13: 4 | M13: =K13*L13 -> 12 | N13: =IF(M13>=20,"Critical",IF(M13>=12,"High",IF(M13>=6,"Medium","Low"))) -> High | O13: Vendor selection considers reputation informally; API keys rotated on ad-hoc basis; SSO integration for major vendors | P13: Weak | Q13: 3 | R13: 4 | S13: =Q13*R13 -> 12 | T13: =IF(S13>=20,"Critical",IF(S13>=12,"High",IF(S13>=6,"Medium","Low"))) -> High | U13: CISO | V13: Mitigate | W13: TRP-009
A14: CRR-010 | B14: Protect (PR) | C14: Configuration Management | D14: Infrastructure drift from security baselines | E14: Production cloud infrastructure deviates from secure configuration baselines over time as developers make ad-hoc changes, introducing security weaknesses (open security groups, excessive IAM permissions, unencrypted volumes). | F14: Human error (developer/ops) | G14: Configuration drift / security regression | H14: No CIS benchmark adoption; no IaC enforcement; no configuration drift detection; AWS resources deployed manually | I14: AWS infrastructure (VPCs, EC2, RDS, IAM) | J14: Restricted (hosts payment data) | K14: 4 | L14: 4 | M14: =K14*L14 -> 16 | N14: =IF(M14>=20,"Critical",IF(M14>=12,"High",IF(M14>=6,"Medium","Low"))) -> High | O14: Basic AWS tagging; some Terraform modules (inconsistent adoption); quarterly manual security review | P14: Weak | Q14: 4 | R14: 4 | S14: =Q14*R14 -> 16 | T14: =IF(S14>=20,"Critical",IF(S14>=12,"High",IF(S14>=6,"Medium","Low"))) -> High | U14: DevOps Lead | V14: Mitigate | W14: TRP-010
A15: CRR-011 | B15: Recover (RC) | C15: Business Continuity | D15: Extended outage of corporate IT during disaster | E15: Disaster (fire, flood, prolonged power outage at data centre) renders corporate IT systems (email, HR, Jira, Slack) unavailable for >24 hours. BCP covers payment engine only; corporate systems have no documented RTO/RPO. | F15: Environmental / infrastructure failure | G15: Service disruption / data unavailability | H15: BCP covers payment processing only; no DR plan for corporate IT; RTO/RPO not defined for non-payment systems | I15: Corporate IT systems (email, Jira, Slack, HRIS) | J15: Internal | K15: 2 | L15: 4 | M15: =K15*L15 -> 8 | N15: =IF(M15>=20,"Critical",IF(M15>=12,"High",IF(M15>=6,"Medium","Low"))) -> Medium | O15: AWS multi-AZ for payment platform; daily backups of production databases; BCP tested annually (payment engine only) | P15: Moderate | Q15: 2 | R15: 3 | S15: =Q15*R15 -> 6 | T15: =IF(S15>=20,"Critical",IF(S15>=12,"High",IF(S15>=6,"Medium","Low"))) -> Medium | U15: IT Manager | V15: Mitigate | W15: TRP-011
A16: CRR-012 | B16: Protect (PR) | C16: Physical Security | D16: Unauthorised physical access via tailgating | E16: Unauthorised individual gains physical access to office space by tailgating through the main entrance, potentially accessing sensitive areas including the server room, whiteboards with architecture diagrams, or unattended workstations. | F16: Social engineering (physical) | G16: Tailgating / impersonation | H16: No anti-tailgating controls at main entrance; no visitor escort policy; CCTV does not cover all sensitive areas | I16: Server room + office workstations + whiteboards | J16: Internal / Confidential | K16: 2 | L16: 3 | M16: =K16*L16 -> 6 | N16: =IF(M16>=20,"Critical",IF(M16>=12,"High",IF(M16>=6,"Medium","Low"))) -> Medium | O16: Grade-A building with lobby security; biometric access to server room; CCTV in server room and reception; 30-day video retention | P16: Strong | Q16: 1 | R16: 2 | S16: =Q16*R16 -> 2 | T16: =IF(S16>=20,"Critical",IF(S16>=12,"High",IF(S16>=6,"Medium","Low"))) -> Low | U16: Office Manager | V16: Accept | W16: N/A
... A20: CRR-016 | B20: Protect (PR) | C20: Access Control | D20: Orphaned accounts after employee departure | E20: SaaS application accounts (Slack, Jira, Figma, GitHub) remain active after employee departure due to incomplete offboarding checklist, providing potential attack vector if credentials are compromised post-employment. | F20: Process gap / former employee | G20: Account persistence / credential reuse | H20: Offboarding checklist does not cover SaaS access revocation; no automated provisioning/deprovisioning; no periodic SaaS access review | I20: SaaS applications (Slack, Jira, Figma, GitHub) | J20: Confidential (source code + internal comms) | K20: 3 | L20: 3 | M20: =K20*L20 -> 9 | N20: =IF(M20>=20,"Critical",IF(M20>=12,"High",IF(M20>=6,"Medium","Low"))) -> Medium | O20: AD account disabled on last day; laptop returned; badge deactivated; exit interview conducted | P20: Moderate | Q20: 2 | R20: 2 | S20: =Q20*R20 -> 4 | T20: =IF(S20>=20,"Critical",IF(S20>=12,"High",IF(S20>=6,"Medium","Low"))) -> Low | U20: IT Manager / HR | V20: Mitigate | W20: TRP-015

Sheet Heat Map
A1: Likelihood-Impact Heat Map — Residual Risk
E3: I M P A C T →
C4: 1 Negligible | D4: 2 Minor | E4: 3 Moderate | F4: 4 Major | G4: 5 Catastrophic
A5: L I K E L I H O O D ↑ | B5: 1 Very Low
B6: 2 Low | F6: Critical (16) CRR-010 | G6: Critical (20) CRR-002, CRR-003
B7: 3 Moderate | E7: High (9) CRR-006, CRR-008 CRR-007 CRR-013 CRR-014 | F7: High (12) CRR-001 CRR-005 CRR-009 | G7: Critical (15) CRR-004
B8: 4 High | D8: Medium (4) CRR-016 | E8: Medium (6) CRR-011 CRR-015
B9: 5 Very High | D9: Low (2) CRR-012
B12: Legend:
C13: Critical (20–25)
C14: High (12–19)
C15: Medium (6–11)
C16: Low (1–5)

Sheet Treatment Plan
A1: Risk Treatment Plan — PayWave Solutions Pte. Ltd.
A2: Linked to Cyber Risk Register v1.0 | Treatment timeline: 12 months | Version 1.0
A4: Ref | B4: Risk ID | C4: Treatment Decision | D4: Treatment Action | E4: Expected Outcome | F4: Owner | G4: Priority | H4: Target Date | I4: Estimated Cost (SGD) | J4: Dependencies | K4: Success KPI | L4: Status
A5: TRP-001 | B5: CRR-001 | C5: Mitigate | D5: Deploy PAM solution (CyberArk or Delinea) for all privileged accounts. Remove standing developer access to production databases. Implement just-in-time (JIT) access with session recording and 4-hour maximum duration. Create break-glass procedure with mandatory post-incident review. | E5: Zero standing privileged access to production. All privileged sessions recorded and auditable. Break-glass events reviewed within 24 hours. | F5: CTO | G5: P1 | H5: Month 2 | I5: $25,000–40,000/yr | J5: Vendor selection; dev team onboarding; break-glass SOP approval | K5: 0 standing dev accounts with prod access; 100% privileged sessions recorded; break-glass usage <2x/month | L5: Not Started
A6: TRP-002 | B6: CRR-002 | C6: Mitigate | D6: Deploy EDR solution (CrowdStrike Falcon) on all endpoints (company laptops, desktops, servers). Deploy SIEM (Microsoft Sentinel) with correlation rules for ransomware indicators. Implement automated containment playbook for ransomware detection. Extend IR plan to cover ransomware scenarios with tabletop exercise. | E6: Ransomware detected within minutes. Automated containment isolates affected endpoints. CSIRT responds within 1 hour of alert. | F6: CISO | G6: P1 | H6: Month 3 | I6: $45,000–70,000/yr | J6: EDR vendor selection; SIEM integration with CloudTrail/ELK; IR plan expansion; CSIRT formation | K6: MTTD for ransomware <15 minutes; automated containment <5 minutes; tabletop exercise completed quarterly | L6: Not Started
A7: TRP-003 | B7: CRR-003 | C7: Mitigate | D7: Deploy CSPM tool (Prowler for AWS or AWS Security Hub with conformance packs). Enforce Infrastructure-as-Code (Terraform) for all AWS resource provisioning with pre-commit security guardrails (Checkov/tfsec). Block manual S3 bucket creation via SCP. Implement automated public-access alerting with auto-remediation. | E7: All S3 buckets private by default. Configuration drift detected within 1 hour. Manual resource creation blocked. | F7: DevOps Lead | G7: P1 | H7: Month 2 | I7: $15,000–25,000/yr | J7: IaC adoption by dev teams; SCP policy approval; CSPM vendor selection | K7: 0 publicly accessible S3 buckets; 100% of new infra via IaC; CSPM scan pass rate >95% | L7: Not Started
A8: TRP-004 | B8: CRR-004 | C8: Mitigate | D8: Create PDPA breach notification SOP with step-by-step workflow, template notification letters (to PDPC and affected individuals), and escalation path. Build regulatory authority contact register (MAS, PDPC, CSA Singapore, SPF). Conduct breach notification tabletop exercise. Train DPO and legal team. | E8: Breach notification process documented and tested. PDPC notified within 72 hours of qualifying breach. Contact register maintained and current. | F8: DPO / Legal | G8: P1 | H8: Month 1 | I8: $5,000–10,000 | J8: Legal review of notification templates; PDPC guidance review; tabletop scenario development | K8: Breach notification SOP published; tabletop completed with <72hr notification achieved; contact register reviewed quarterly | L8: Not Started
A9: TRP-005 | B9: CRR-005 | C9: Mitigate | D9: Deploy continuous vulnerability scanner (Qualys or Tenable) for infrastructure and web applications. Define and enforce patch SLAs: Critical 48 hours, High 7 days, Medium 30 days, Low 90 days. Create vulnerability register with tracking dashboard. Integrate scanner findings into Jira for developer remediation. | E9: Continuous visibility of all vulnerabilities. Critical vulnerabilities patched within 48 hours. Vulnerability backlog managed and reducing. | F9: DevOps Lead | G9: P1 | H9: Month 2 | I9: $20,000–35,000/yr | J9: Scanner deployment across all environments; patch SLA approval; Jira integration | K9: Zero critical vulns >48 hours; high vulns >7 days <5%; scanner coverage 100% of prod assets | L9: Not Started
A10: TRP-006 | B10: CRR-006 | C10: Mitigate | D10: Implement role-based security awareness training: secure coding module for engineers (OWASP Top 10 + secure API design), financial fraud awareness for finance team, PII handling for HR and customer support. Deploy advanced phishing simulation (monthly cadence, varied scenarios). Enforce MFA on all SaaS applications via Okta conditional access. Implement DMARC enforcement on corporate email domain. | E10: Phishing click rate reduced to <10%. All SaaS applications protected by MFA. Email domain protected against spoofing. | F10: CISO / HR | G10: P2 | H10: Month 4 | I10: $15,000–25,000 | J10: LMS procurement; phishing sim platform; Okta conditional access configuration; DMARC DNS records | K10: Phishing click rate <10% (from 40%); MFA coverage 100% SaaS apps; DMARC at p=reject | L10: Not Started
A11: TRP-007 | B11: CRR-007 | C11: Mitigate | D11: Deploy endpoint DLP agent (Microsoft Purview or Symantec) with rules for PII and source code detection. Disable USB mass storage on all company endpoints via GPO/MDM. Enforce MDM enrolment for all BYOD devices accessing corporate email. Draft and publish Acceptable Use Policy covering personal cloud storage, USB devices, and BYOD. | E11: Data exfiltration channels closed. USB storage blocked. BYOD devices managed. AUP signed by all staff. | F11: IT Manager | G11: P2 | H11: Month 4 | I11: $12,000–20,000/yr | J11: DLP solution selection; GPO deployment; AUP drafting and legal review; MDM policy update | K11: USB storage blocked on 100% endpoints; BYOD MDM compliance 100%; AUP signed by 100% staff within 30 days | L11: Not Started
A12: TRP-008 | B12: CRR-008 | C12: Mitigate | D12: Integrate SAST tool (SonarQube) into CI/CD pipeline — all PRs must pass security scan before merge. Add DAST scanner (OWASP ZAP) to staging environment deployment pipeline. Publish secure coding guidelines document (based on OWASP ASVS). Appoint security champion per engineering squad (4 champions). Conduct quarterly secure coding workshops. | E12: Security vulnerabilities caught before production. Developers trained in secure coding. Security embedded in engineering culture. | F12: Engineering Lead | G12: P2 | H12: Month 5 | I12: $18,000–30,000/yr | J12: SAST/DAST tool selection; CI/CD pipeline modification; secure coding guidelines drafting; champion nomination | K12: Zero critical/high SAST findings in production deployments; DAST scan pass rate >90%; security champion coverage 100% of squads | L12: Not Started
A13: TRP-009 | B13: CRR-009 | C13: Mitigate | D13: Establish formal Third-Party Risk Management (TPRM) program. Design vendor risk questionnaire covering data handling, security controls, business continuity, and sub-contractors. Conduct security assessments of all critical SaaS vendors (Tier 1). Add security requirements to vendor contracts (data protection clauses, breach notification, right to audit). Implement API key rotation policy (90-day maximum). | E13: All critical vendors assessed for security posture. Contractual security requirements in place. API keys rotated regularly. | F13: CISO | G13: P2 | H13: Month 5 | I13: $10,000–15,000 | J13: Vendor questionnaire design; legal review of contract clauses; vendor inventory compilation; API key audit | K13: 100% Tier 1 vendors assessed; security clauses in 100% of new/renewed contracts; API keys rotated within 90 days | L13: Not Started
A14: TRP-010 | B14: CRR-010 | C14: Mitigate | D14: Adopt CIS benchmarks for AWS (CIS AWS Foundations Benchmark v3.0) and endpoint OS (CIS Ubuntu 24.04). Enforce all new infrastructure via Terraform with pre-commit security scanning (Checkov). Deploy AWS Config rules for continuous configuration compliance monitoring. Implement automated drift detection with alerting to DevOps Slack channel and auto-remediation for critical drifts. | E14: All infrastructure deployed from hardened baselines. Configuration drift detected and alerted within 1 hour. Compliance score tracked and improving. | F14: DevOps Lead | G14: P1 | H14: Month 3 | I14: $10,000–15,000 | J14: CIS benchmark customisation; Terraform module library; AWS Config rule deployment; drift alerting setup | K14: CIS benchmark compliance >85% on monthly scan; 100% new infra via IaC; drift alerts resolved within 4 hours | L14: Not Started
A15: TRP-011 | B15: CRR-011 | C15: Mitigate | D15: Extend BCP to cover all corporate IT systems (email, Jira, Slack, HRIS, finance). Define RTO and RPO targets for each corporate system. Conduct DR test covering both payment and corporate IT systems. Document failover procedures for each critical system. | E15: BCP covers full organisational scope. RTO/RPO defined and tested for all critical systems. DR test validates recovery capability. | F15: IT Manager | G15: P2 | H15: Month 6 | I15: $8,000–15,000 | J15: BCP scope expansion; RTO/RPO workshops with each department; DR test planning | K15: BCP v2.0 covering all critical systems; DR test meets RTO/RPO targets; annual DR test cadence established | L15: Not Started
... A19: TRP-015 | B19: CRR-016 | C19: Mitigate | D19: Add SaaS access revocation to offboarding checklist (Slack, Jira, Figma, GitHub, AWS, all Okta-integrated apps). Implement automated deprovisioning via Okta lifecycle management for integrated apps. Conduct quarterly SaaS access review for orphaned accounts. Send NDA reminder email on employee's last day. | E19: Zero orphaned SaaS accounts after employee departure. Automated deprovisioning for Okta-integrated apps. Quarterly review catches non-integrated app access. | F19: IT Manager / HR | G19: P3 | H19: Month 7 | I19: $3,000–5,000 | J19: Okta lifecycle configuration; offboarding checklist update; SaaS inventory compilation | K19: Zero orphaned accounts found in quarterly review; deprovisioning automated for >80% of SaaS apps; NDA reminder sent to 100% of departing staff | L19: Not Started
